[
 {
  "id": "sve-001",
  "localId": "001",
  "name": "Grass Energy",
  "category": "Energy",
  "rarity": "Common",
  "dexIds": [],
  "image": null,
  "market": {
   "trend": 0.03,
   "avg30": 0.03,
   "low": 0.02,
   "updated": "2026-07-21T08:02:25.039Z"
  },
  "preset": {
   "rarity": "common",
   "era": "modern",
   "popularity": "c"
  }
 },
 {
  "id": "sve-002",
  "localId": "002",
  "name": "Fire Energy",
  "category": "Energy",
  "rarity": "Common",
  "dexIds": [],
  "image": null,
  "market": {
   "trend": 0.03,
   "avg30": 0.03,
   "low": 0.02,
   "updated": "2026-07-21T08:02:31.372Z"
  },
  "preset": {
   "rarity": "common",
   "era": "modern",
   "popularity": "c"
  }
 },
 {
  "id": "sve-003",
  "localId": "003",
  "name": "Water Energy",
  "category": "Energy",
  "rarity": "Common",
  "dexIds": [],
  "image": null,
  "market": {
   "trend": 0.02,
   "avg30": 0.03,
   "low": 0.02,
   "updated": "2026-07-21T08:02:25.039Z"
  },
  "preset": {
   "rarity": "common",
   "era": "modern",
   "popularity": "c"
  }
 },
 {
  "id": "sve-004",
  "localId": "004",
  "name": "Lightning Energy",
  "category": "Energy",
  "rarity": "Common",
  "dexIds": [],
  "image": null,
  "market": {
   "trend": 0.03,
   "avg30": 0.02,
   "low": 0.02,
   "updated": "2026-07-21T08:02:25.039Z"
  },
  "preset": {
   "rarity": "common",
   "era": "modern",
   "popularity": "c"
  }
 },
 {
  "id": "sve-005",
  "localId": "005",
  "name": "Psychic Energy",
  "category": "Energy",
  "rarity": "Common",
  "dexIds": [],
  "image": null,
  "market": {
   "trend": 0.02,
   "avg30": 0.03,
   "low": 0.02,
   "updated": "2026-07-21T08:02:31.372Z"
  },
  "preset": {
   "rarity": "common",
   "era": "modern",
   "popularity": "c"
  }
 },
 {
  "id": "sve-006",
  "localId": "006",
  "name": "Fighting Energy",
  "category": "Energy",
  "rarity": "Common",
  "dexIds": [],
  "image": null,
  "market": {
   "trend": 0.02,
   "avg30": 0.03,
   "low": 0.02,
   "updated": "2026-07-21T08:02:25.039Z"
  },
  "preset": {
   "rarity": "common",
   "era": "modern",
   "popularity": "c"
  }
 },
 {
  "id": "sve-007",
  "localId": "007",
  "name": "Darkness Energy",
  "category": "Energy",
  "rarity": "Common",
  "dexIds": [],
  "image": null,
  "market": {
   "trend": 0.02,
   "avg30": 0.02,
   "low": 0.02,
   "updated": "2026-07-21T08:02:25.039Z"
  },
  "preset": {
   "rarity": "common",
   "era": "modern",
   "popularity": "c"
  }
 },
 {
  "id": "sve-008",
  "localId": "008",
  "name": "Metal Energy",
  "category": "Energy",
  "rarity": "Common",
  "dexIds": [],
  "image": null,
  "market": {
   "trend": 0.06,
   "avg30": 0.03,
   "low": 0.02,
   "updated": "2026-07-21T08:02:25.039Z"
  },
  "preset": {
   "rarity": "common",
   "era": "modern",
   "popularity": "c"
  }
 },
 {
  "id": "sve-009",
  "localId": "009",
  "name": "Grass Energy",
  "category": "Energy",
  "rarity": "Common",
  "dexIds": [],
  "image": null,
  "market": {
   "trend": 0.02,
   "avg30": 0.03,
   "low": 0.02,
   "updated": "2026-07-21T08:02:25.039Z"
  },
  "preset": {
   "rarity": "common",
   "era": "modern",
   "popularity": "c"
  }
 },
 {
  "id": "sve-010",
  "localId": "010",
  "name": "Fire Energy",
  "category": "Energy",
  "rarity": "Common",
  "dexIds": [],
  "image": null,
  "market": {
   "trend": 0.03,
   "avg30": 0.03,
   "low": 0.02,
   "updated": "2026-07-21T08:02:31.372Z"
  },
  "preset": {
   "rarity": "common",
   "era": "modern",
   "popularity": "c"
  }
 },
 {
  "id": "sve-011",
  "localId": "011",
  "name": "Water Energy",
  "category": "Energy",
  "rarity": "Common",
  "dexIds": [],
  "image": null,
  "market": {
   "trend": 0.03,
   "avg30": 0.03,
   "low": 0.02,
   "updated": "2026-07-21T08:02:25.039Z"
  },
  "preset": {
   "rarity": "common",
   "era": "modern",
   "popularity": "c"
  }
 },
 {
  "id": "sve-012",
  "localId": "012",
  "name": "Lightning Energy",
  "category": "Energy",
  "rarity": "Common",
  "dexIds": [],
  "image": null,
  "market": {
   "trend": 0.04,
   "avg30": 0.03,
   "low": 0.02,
   "updated": "2026-07-21T08:02:25.039Z"
  },
  "preset": {
   "rarity": "common",
   "era": "modern",
   "popularity": "c"
  }
 },
 {
  "id": "sve-013",
  "localId": "013",
  "name": "Psychic Energy",
  "category": "Energy",
  "rarity": "Common",
  "dexIds": [],
  "image": null,
  "market": {
   "trend": 0.02,
   "avg30": 0.03,
   "low": 0.02,
   "updated": "2026-07-21T08:02:31.372Z"
  },
  "preset": {
   "rarity": "common",
   "era": "modern",
   "popularity": "c"
  }
 },
 {
  "id": "sve-014",
  "localId": "014",
  "name": "Fighting Energy",
  "category": "Energy",
  "rarity": "Common",
  "dexIds": [],
  "image": null,
  "market": {
   "trend": 0.02,
   "avg30": 0.03,
   "low": 0.02,
   "updated": "2026-07-21T08:02:25.285Z"
  },
  "preset": {
   "rarity": "common",
   "era": "modern",
   "popularity": "c"
  }
 },
 {
  "id": "sve-015",
  "localId": "015",
  "name": "Darkness Energy",
  "category": "Energy",
  "rarity": "Common",
  "dexIds": [],
  "image": null,
  "market": {
   "trend": 0.03,
   "avg30": 0.03,
   "low": 0.02,
   "updated": "2026-07-21T08:02:31.372Z"
  },
  "preset": {
   "rarity": "common",
   "era": "modern",
   "popularity": "c"
  }
 },
 {
  "id": "sve-016",
  "localId": "016",
  "name": "Metal Energy",
  "category": "Energy",
  "rarity": "Common",
  "dexIds": [],
  "image": null,
  "market": {
   "trend": 0.04,
   "avg30": 0.03,
   "low": 0.02,
   "updated": "2026-07-21T08:02:25.039Z"
  },
  "preset": {
   "rarity": "common",
   "era": "modern",
   "popularity": "c"
  }
 },
 {
  "id": "sve-017",
  "localId": "017",
  "name": "Grass Energy",
  "category": "Energy",
  "rarity": "Common",
  "dexIds": [],
  "image": null,
  "market": {
   "trend": 0.04,
   "avg30": 0.04,
   "low": 0.02,
   "updated": "2026-07-21T08:02:25.039Z"
  },
  "preset": {
   "rarity": "common",
   "era": "modern",
   "popularity": "c"
  }
 },
 {
  "id": "sve-018",
  "localId": "018",
  "name": "Fire Energy",
  "category": "Energy",
  "rarity": "Common",
  "dexIds": [],
  "image": null,
  "market": {
   "trend": 0.03,
   "avg30": 0.04,
   "low": 0.02,
   "updated": "2026-07-21T08:02:25.039Z"
  },
  "preset": {
   "rarity": "common",
   "era": "modern",
   "popularity": "c"
  }
 },
 {
  "id": "sve-019",
  "localId": "019",
  "name": "Water Energy",
  "category": "Energy",
  "rarity": "Common",
  "dexIds": [],
  "image": null,
  "market": {
   "trend": 0.05,
   "avg30": 0.04,
   "low": 0.02,
   "updated": "2026-07-21T08:02:31.372Z"
  },
  "preset": {
   "rarity": "common",
   "era": "modern",
   "popularity": "c"
  }
 },
 {
  "id": "sve-020",
  "localId": "020",
  "name": "Lightning Energy",
  "category": "Energy",
  "rarity": "Common",
  "dexIds": [],
  "image": null,
  "market": {
   "trend": 0.02,
   "avg30": 0.04,
   "low": 0.02,
   "updated": "2026-07-21T08:02:25.039Z"
  },
  "preset": {
   "rarity": "common",
   "era": "modern",
   "popularity": "c"
  }
 },
 {
  "id": "sve-021",
  "localId": "021",
  "name": "Psychic Energy",
  "category": "Energy",
  "rarity": "Common",
  "dexIds": [],
  "image": null,
  "market": {
   "trend": 0.05,
   "avg30": 0.04,
   "low": 0.02,
   "updated": "2026-07-21T08:02:25.039Z"
  },
  "preset": {
   "rarity": "common",
   "era": "modern",
   "popularity": "c"
  }
 },
 {
  "id": "sve-022",
  "localId": "022",
  "name": "Fighting Energy",
  "category": "Energy",
  "rarity": "Common",
  "dexIds": [],
  "image": null,
  "market": {
   "trend": 0.12,
   "avg30": 0.05,
   "low": 0.02,
   "updated": "2026-07-21T08:02:25.039Z"
  },
  "preset": {
   "rarity": "common",
   "era": "modern",
   "popularity": "c"
  }
 },
 {
  "id": "sve-023",
  "localId": "023",
  "name": "Darkness Energy",
  "category": "Energy",
  "rarity": "Common",
  "dexIds": [],
  "image": null,
  "market": {
   "trend": 0.02,
   "avg30": 0.05,
   "low": 0.02,
   "updated": "2026-07-21T08:02:25.039Z"
  },
  "preset": {
   "rarity": "common",
   "era": "modern",
   "popularity": "c"
  }
 },
 {
  "id": "sve-024",
  "localId": "024",
  "name": "Metal Energy",
  "category": "Energy",
  "rarity": "Common",
  "dexIds": [],
  "image": null,
  "market": {
   "trend": 0.05,
   "avg30": 0.04,
   "low": 0.02,
   "updated": "2026-07-21T08:02:25.039Z"
  },
  "preset": {
   "rarity": "common",
   "era": "modern",
   "popularity": "c"
  }
 }
]